{
    "total": [
        {
            "id": "61551544731320",
            "count": 6
        },
        {
            "id": "100090562700474",
            "count": 10
        }
    ],
    "week": [
        {
            "id": "61551544731320",
            "count": 6
        },
        {
            "id": "100090562700474",
            "count": 10
        }
    ],
    "day": [
        {
            "id": "61551544731320",
            "count": 6
        },
        {
            "id": "100090562700474",
            "count": 10
        }
    ],
    "time": 6
}